{
  "search_examples": {
    "by_filename": {
      "query": "common_spiritwheel1.scb",
      "result": {
        "filename": "common_spiritwheel1.scb",
        "type": "scb",
        "path": "SCB/common_spiritwheel1.scb",
        "size": 84428,
        "hash": "59770fe7164673de",
        "champion": null,
        "skin": "base",
        "champion_skin": null
      }
    },
    "champion_files": {
      "yasuo": {
        "sco": [
          {
            "filename": "yasuo_base_r_sword_wind2.sco",
            "type": "sco",
            "path": "SCO/yasuo_base_r_sword_wind2.sco",
            "size": 46229,
            "hash": "7c7589e3ee9898df",
            "champion": "yasuo",
            "skin": "base",
            "champion_skin": "yasuo_base"
          }
        ],
        "scb": [
          {
            "filename": "chibiyasuo_dragonmancer_finisher_c004tovfx.scb",
            "type": "scb",
            "path": "SCB/chibiyasuo_dragonmancer_finisher_c004tovfx.scb",
            "size": 11592,
            "hash": "44d4e25236c5fe44",
            "champion": "yasuo",
            "skin": "base",
            "champion_skin": "yasuo_base"
          },
          {
            "filename": "petchibiyasuo_prestige_env_mountain_mesh.scb",
            "type": "scb",
            "path": "SCB/petchibiyasuo_prestige_env_mountain_mesh.scb",
            "size": 176912,
            "hash": "f05dbec6586c13c1",
            "champion": "yasuo",
            "skin": "prestige",
            "champion_skin": "yasuo_prestige"
          },
          {
            "filename": "petchibiyasuo_prestige_env_sky_mesh.scb",
            "type": "scb",
            "path": "SCB/petchibiyasuo_prestige_env_sky_mesh.scb",
            "size": 50248,
            "hash": "9f338d5d00a8ca53",
            "champion": "yasuo",
            "skin": "prestige",
            "champion_skin": "yasuo_prestige"
          },
          {
            "filename": "petchibiyasuo_skin1_emote_base_laugh_trail01.scb",
            "type": "scb",
            "path": "SCB/petchibiyasuo_skin1_emote_base_laugh_trail01.scb",
            "size": 11592,
            "hash": "f3d06b32d2d0c7e6",
            "champion": "yasuo",
            "skin": "skin_1",
            "champion_skin": "yasuo_skin_1"
          },
          {
            "filename": "petchibiyasuo_skin1_emote_base_laugh_trail02.scb",
            "type": "scb",
            "path": "SCB/petchibiyasuo_skin1_emote_base_laugh_trail02.scb",
            "size": 9272,
            "hash": "11896d601a6b672e",
            "champion": "yasuo",
            "skin": "skin_1",
            "champion_skin": "yasuo_skin_1"
          },
          {
            "filename": "petchibiyasuo_skin1_emote_base_laugh_trail03.scb",
            "type": "scb",
            "path": "SCB/petchibiyasuo_skin1_emote_base_laugh_trail03.scb",
            "size": 11592,
            "hash": "fb4722971281d061",
            "champion": "yasuo",
            "skin": "skin_1",
            "champion_skin": "yasuo_skin_1"
          },
          {
            "filename": "petchibiyasuo_skin1_emote_base_laugh_trail04.scb",
            "type": "scb",
            "path": "SCB/petchibiyasuo_skin1_emote_base_laugh_trail04.scb",
            "size": 11592,
            "hash": "f52aa2e033cd277e",
            "champion": "yasuo",
            "skin": "skin_1",
            "champion_skin": "yasuo_skin_1"
          },
          {
            "filename": "petchibiyasuo_skin1_emote_base_laugh_windwall.scb",
            "type": "scb",
            "path": "SCB/petchibiyasuo_skin1_emote_base_laugh_windwall.scb",
            "size": 26480,
            "hash": "34f4c9dd11e25d52",
            "champion": "yasuo",
            "skin": "skin_1",
            "champion_skin": "yasuo_skin_1"
          },
          {
            "filename": "petchibiyasuo_skin1_emote_base_taunt_swing02.scb",
            "type": "scb",
            "path": "SCB/petchibiyasuo_skin1_emote_base_taunt_swing02.scb",
            "size": 11592,
            "hash": "8293ee6cbd5db06a",
            "champion": "yasuo",
            "skin": "skin_1",
            "champion_skin": "yasuo_skin_1"
          },
          {
            "filename": "petchibiyasuo_skin1_idle_funnel_mis_2.scb",
            "type": "scb",
            "path": "SCB/petchibiyasuo_skin1_idle_funnel_mis_2.scb",
            "size": 20736,
            "hash": "d5100f8f19e0e05e",
            "champion": "yasuo",
            "skin": "skin_1",
            "champion_skin": "yasuo_skin_1"
          },
          {
            "filename": "petchibiyasuo_skin2_c.scb",
            "type": "scb",
            "path": "SCB/petchibiyasuo_skin2_c.scb",
            "size": 44032,
            "hash": "7ab4753bf8ab6a86",
            "champion": "yasuo",
            "skin": "skin_2",
            "champion_skin": "yasuo_skin_2"
          },
          {
            "filename": "petchibiyasuo_skin2_emote_daoguang.scb",
            "type": "scb",
            "path": "SCB/petchibiyasuo_skin2_emote_daoguang.scb",
            "size": 34652,
            "hash": "86cf78fe79cf5d96",
            "champion": "yasuo",
            "skin": "skin_2",
            "champion_skin": "yasuo_skin_2"
          },
          {
            "filename": "petchibiyasuo_skin2_emote_dragonmancer_pattern.scb",
            "type": "scb",
            "path": "SCB/petchibiyasuo_skin2_emote_dragonmancer_pattern.scb",
            "size": 54960,
            "hash": "f7d512ce49db0b60",
            "champion": "yasuo",
            "skin": "skin_2",
            "champion_skin": "yasuo_skin_2"
          },
          {
            "filename": "petchibiyasuo_skin2_finisher_hit_wind01.scb",
            "type": "scb",
            "path": "SCB/petchibiyasuo_skin2_finisher_hit_wind01.scb",
            "size": 11592,
            "hash": "29242f27ebd7bd0b",
            "champion": "yasuo",
            "skin": "skin_2",
            "champion_skin": "yasuo_skin_2"
          },
          {
            "filename": "petchibiyasuo_skin2_plane_1.scb",
            "type": "scb",
            "path": "SCB/petchibiyasuo_skin2_plane_1.scb",
            "size": 3792,
            "hash": "44df5630c899789b",
            "champion": "yasuo",
            "skin": "skin_2",
            "champion_skin": "yasuo_skin_2"
          },
          {
            "filename": "petchibiyasuo_skin2_plane_2.scb",
            "type": "scb",
            "path": "SCB/petchibiyasuo_skin2_plane_2.scb",
            "size": 3792,
            "hash": "5e1d1a172664c25b",
            "champion": "yasuo",
            "skin": "skin_2",
            "champion_skin": "yasuo_skin_2"
          },
          {
            "filename": "petchibiyasuo_skin2_qiliu.scb",
            "type": "scb",
            "path": "SCB/petchibiyasuo_skin2_qiliu.scb",
            "size": 78412,
            "hash": "1c56a53ed2a9ebc7",
            "champion": "yasuo",
            "skin": "skin_2",
            "champion_skin": "yasuo_skin_2"
          },
          {
            "filename": "petchibiyasuo_skin2_skybox.scb",
            "type": "scb",
            "path": "SCB/petchibiyasuo_skin2_skybox.scb",
            "size": 44844,
            "hash": "8c622f41f77ccdb7",
            "champion": "yasuo",
            "skin": "skin_2",
            "champion_skin": "yasuo_skin_2"
          },
          {
            "filename": "petchibiyasuo_skin2_smoke.scb",
            "type": "scb",
            "path": "SCB/petchibiyasuo_skin2_smoke.scb",
            "size": 13200,
            "hash": "dccc844b663f5b10",
            "champion": "yasuo",
            "skin": "skin_2",
            "champion_skin": "yasuo_skin_2"
          },
          {
            "filename": "petchibiyasuo_skin2_speedline_4.scb",
            "type": "scb",
            "path": "SCB/petchibiyasuo_skin2_speedline_4.scb",
            "size": 191724,
            "hash": "a09fe9dabfec476f",
            "champion": "yasuo",
            "skin": "skin_2",
            "champion_skin": "yasuo_skin_2"
          },
          {
            "filename": "petchibiyasuo_skin3_emote_windwall_mesh.scb",
            "type": "scb",
            "path": "SCB/petchibiyasuo_skin3_emote_windwall_mesh.scb",
            "size": 52392,
            "hash": "2c0182796f017be3",
            "champion": "yasuo",
            "skin": "skin_3",
            "champion_skin": "yasuo_skin_3"
          },
          {
            "filename": "petchibiyasuo_skin3_emote_windwall_mesh_diamonds.scb",
            "type": "scb",
            "path": "SCB/petchibiyasuo_skin3_emote_windwall_mesh_diamonds.scb",
            "size": 8592,
            "hash": "17b1388e8072b82b",
            "champion": "yasuo",
            "skin": "skin_3",
            "champion_skin": "yasuo_skin_3"
          },
          {
            "filename": "petchibiyasuo_skin3_emote_windwall_mesh_dragon.scb",
            "type": "scb",
            "path": "SCB/petchibiyasuo_skin3_emote_windwall_mesh_dragon.scb",
            "size": 8176,
            "hash": "bde27fbd3b31fd96",
            "champion": "yasuo",
            "skin": "skin_3",
            "champion_skin": "yasuo_skin_3"
          },
          {
            "filename": "petchibiyasuo_skin3_emote_windwall_noise_wind.scb",
            "type": "scb",
            "path": "SCB/petchibiyasuo_skin3_emote_windwall_noise_wind.scb",
            "size": 8176,
            "hash": "84c03dc39c459d09",
            "champion": "yasuo",
            "skin": "skin_3",
            "champion_skin": "yasuo_skin_3"
          },
          {
            "filename": "petchibiyasuo_skin3_finisher_cloudenv001.scb",
            "type": "scb",
            "path": "SCB/petchibiyasuo_skin3_finisher_cloudenv001.scb",
            "size": 15848,
            "hash": "93eae23ea254a14c",
            "champion": "yasuo",
            "skin": "skin_3",
            "champion_skin": "yasuo_skin_3"
          },
          {
            "filename": "petchibiyasuo_skin3_finisher_cloudenv002.scb",
            "type": "scb",
            "path": "SCB/petchibiyasuo_skin3_finisher_cloudenv002.scb",
            "size": 3152,
            "hash": "25af01e753b02b23",
            "champion": "yasuo",
            "skin": "skin_3",
            "champion_skin": "yasuo_skin_3"
          },
          {
            "filename": "petchibiyasuo_skin3_finisher_cloudenv003.scb",
            "type": "scb",
            "path": "SCB/petchibiyasuo_skin3_finisher_cloudenv003.scb",
            "size": 3264,
            "hash": "6d5b02a74f1d5e81",
            "champion": "yasuo",
            "skin": "skin_3",
            "champion_skin": "yasuo_skin_3"
          },
          {
            "filename": "petchibiyasuo_skin3_finisher_cloudenv004.scb",
            "type": "scb",
            "path": "SCB/petchibiyasuo_skin3_finisher_cloudenv004.scb",
            "size": 3152,
            "hash": "c43413bb5a6941af",
            "champion": "yasuo",
            "skin": "skin_3",
            "champion_skin": "yasuo_skin_3"
          },
          {
            "filename": "petchibiyasuo_skin3_finisher_cloudenv005.scb",
            "type": "scb",
            "path": "SCB/petchibiyasuo_skin3_finisher_cloudenv005.scb",
            "size": 3152,
            "hash": "1d130ac0ea3d6a3f",
            "champion": "yasuo",
            "skin": "skin_3",
            "champion_skin": "yasuo_skin_3"
          },
          {
            "filename": "petchibiyasuo_skin3__finisher_cloudend.scb",
            "type": "scb",
            "path": "SCB/petchibiyasuo_skin3__finisher_cloudend.scb",
            "size": 13656,
            "hash": "3ae782cd49aa82c8",
            "champion": "yasuo",
            "skin": "skin_3",
            "champion_skin": "yasuo_skin_3"
          },
          {
            "filename": "petchibiyasuo_skin3__finisher_flash01.scb",
            "type": "scb",
            "path": "SCB/petchibiyasuo_skin3__finisher_flash01.scb",
            "size": 21744,
            "hash": "1f439a0b706b9e16",
            "champion": "yasuo",
            "skin": "skin_3",
            "champion_skin": "yasuo_skin_3"
          },
          {
            "filename": "petchibiyasuo_skin3__finisher_flash01_glassshapes.scb",
            "type": "scb",
            "path": "SCB/petchibiyasuo_skin3__finisher_flash01_glassshapes.scb",
            "size": 11328,
            "hash": "d0edd3b5d6406838",
            "champion": "yasuo",
            "skin": "skin_3",
            "champion_skin": "yasuo_skin_3"
          },
          {
            "filename": "petchibiyasuo_skin3__finisher_flash02.scb",
            "type": "scb",
            "path": "SCB/petchibiyasuo_skin3__finisher_flash02.scb",
            "size": 21744,
            "hash": "c28d50d407f99dcc",
            "champion": "yasuo",
            "skin": "skin_3",
            "champion_skin": "yasuo_skin_3"
          },
          {
            "filename": "petchibiyasuo_skin3__finisher_flash02_cy.scb",
            "type": "scb",
            "path": "SCB/petchibiyasuo_skin3__finisher_flash02_cy.scb",
            "size": 26512,
            "hash": "3276fcba3f7fc6c3",
            "champion": "yasuo",
            "skin": "skin_3",
            "champion_skin": "yasuo_skin_3"
          },
          {
            "filename": "petchibiyasuo_skin3__finisher_flash02_glassshapes.scb",
            "type": "scb",
            "path": "SCB/petchibiyasuo_skin3__finisher_flash02_glassshapes.scb",
            "size": 10232,
            "hash": "bc82d3204e18238a",
            "champion": "yasuo",
            "skin": "skin_3",
            "champion_skin": "yasuo_skin_3"
          },
          {
            "filename": "petchibiyasuo_skin3__finisher_flash03.scb",
            "type": "scb",
            "path": "SCB/petchibiyasuo_skin3__finisher_flash03.scb",
            "size": 21744,
            "hash": "1202569030332963",
            "champion": "yasuo",
            "skin": "skin_3",
            "champion_skin": "yasuo_skin_3"
          },
          {
            "filename": "petchibiyasuo_skin3__finisher_flash03_glassshapes.scb",
            "type": "scb",
            "path": "SCB/petchibiyasuo_skin3__finisher_flash03_glassshapes.scb",
            "size": 10564,
            "hash": "e606983283a60c85",
            "champion": "yasuo",
            "skin": "skin_3",
            "champion_skin": "yasuo_skin_3"
          },
          {
            "filename": "petchibiyasuo_skin3__finisher_flash04.scb",
            "type": "scb",
            "path": "SCB/petchibiyasuo_skin3__finisher_flash04.scb",
            "size": 21744,
            "hash": "e2eb3663cf7b8f9d",
            "champion": "yasuo",
            "skin": "skin_3",
            "champion_skin": "yasuo_skin_3"
          },
          {
            "filename": "petchibiyasuo_skin3__finisher_flash04_glassshapes.scb",
            "type": "scb",
            "path": "SCB/petchibiyasuo_skin3__finisher_flash04_glassshapes.scb",
            "size": 13104,
            "hash": "ca0fc9f06507d496",
            "champion": "yasuo",
            "skin": "skin_3",
            "champion_skin": "yasuo_skin_3"
          },
          {
            "filename": "petchibiyasuo_skin3__finisher_flash05.scb",
            "type": "scb",
            "path": "SCB/petchibiyasuo_skin3__finisher_flash05.scb",
            "size": 21744,
            "hash": "ad4b4366d5bf2494",
            "champion": "yasuo",
            "skin": "skin_3",
            "champion_skin": "yasuo_skin_3"
          },
          {
            "filename": "petchibiyasuo_skin3__finisher_flash05_glassshapes.scb",
            "type": "scb",
            "path": "SCB/petchibiyasuo_skin3__finisher_flash05_glassshapes.scb",
            "size": 13684,
            "hash": "0215abbaa42f4be7",
            "champion": "yasuo",
            "skin": "skin_3",
            "champion_skin": "yasuo_skin_3"
          },
          {
            "filename": "petchibiyasuo_skin3__finisher_flash06.scb",
            "type": "scb",
            "path": "SCB/petchibiyasuo_skin3__finisher_flash06.scb",
            "size": 21744,
            "hash": "c830b7d60dfb7eb6",
            "champion": "yasuo",
            "skin": "skin_3",
            "champion_skin": "yasuo_skin_3"
          },
          {
            "filename": "petchibiyasuo_skin3__finisher_flash06_glassshapes.scb",
            "type": "scb",
            "path": "SCB/petchibiyasuo_skin3__finisher_flash06_glassshapes.scb",
            "size": 12856,
            "hash": "118534f04dbf366e",
            "champion": "yasuo",
            "skin": "skin_3",
            "champion_skin": "yasuo_skin_3"
          },
          {
            "filename": "petchibiyasuo_skin3__finisher_plane01.scb",
            "type": "scb",
            "path": "SCB/petchibiyasuo_skin3__finisher_plane01.scb",
            "size": 6720,
            "hash": "b84feb87fd0130c3",
            "champion": "yasuo",
            "skin": "skin_3",
            "champion_skin": "yasuo_skin_3"
          },
          {
            "filename": "petchibiyasuo_skin3__finisher_tmp_transition_intro_trail_01.scb",
            "type": "scb",
            "path": "SCB/petchibiyasuo_skin3__finisher_tmp_transition_intro_trail_01.scb",
            "size": 69952,
            "hash": "cce2777685e2a224",
            "champion": "yasuo",
            "skin": "skin_3",
            "champion_skin": "yasuo_skin_3"
          },
          {
            "filename": "petchibiyasuo_skin3__petchibized_base_boom_helix03.scb",
            "type": "scb",
            "path": "SCB/petchibiyasuo_skin3__petchibized_base_boom_helix03.scb",
            "size": 26816,
            "hash": "eee1c667a6d2d079",
            "champion": "yasuo",
            "skin": "skin_3",
            "champion_skin": "yasuo_skin_3"
          },
          {
            "filename": "petchibiyasuo_skin3__prestige_finisher_swordlight01.scb",
            "type": "scb",
            "path": "SCB/petchibiyasuo_skin3__prestige_finisher_swordlight01.scb",
            "size": 10992,
            "hash": "e51175c58034d38f",
            "champion": "yasuo",
            "skin": "skin_3",
            "champion_skin": "yasuo_skin_3"
          },
          {
            "filename": "petchibiyasuo_skin3__skybox_cloud_a.scb",
            "type": "scb",
            "path": "SCB/petchibiyasuo_skin3__skybox_cloud_a.scb",
            "size": 13152,
            "hash": "eb0c449f82eb4467",
            "champion": "yasuo",
            "skin": "skin_3",
            "champion_skin": "yasuo_skin_3"
          },
          {
            "filename": "strawberry_yasuo_base_eq_swipe_01.strawberryrebuild.scb",
            "type": "scb",
            "path": "SCB/strawberry_yasuo_base_eq_swipe_01.strawberryrebuild.scb",
            "size": 19632,
            "hash": "d2b2c70311eede5f",
            "champion": "yasuo",
            "skin": "base",
            "champion_skin": "yasuo_base"
          },
          {
            "filename": "strawberry_yasuo_base_e_q_blade_trail.strawberryrebuild.scb",
            "type": "scb",
            "path": "SCB/strawberry_yasuo_base_e_q_blade_trail.strawberryrebuild.scb",
            "size": 129576,
            "hash": "01518615c9572f75",
            "champion": "yasuo",
            "skin": "base",
            "champion_skin": "yasuo_base"
          },
          {
            "filename": "strawberry_yasuo_base_q_mis_up001.strawberryrebuild.scb",
            "type": "scb",
            "path": "SCB/strawberry_yasuo_base_q_mis_up001.strawberryrebuild.scb",
            "size": 23488,
            "hash": "68b111f26a99e5ae",
            "champion": "yasuo",
            "skin": "base",
            "champion_skin": "yasuo_base"
          },
          {
            "filename": "strawberry_yasuo_base_wind005_out_back02.strawberryrebuild.scb",
            "type": "scb",
            "path": "SCB/strawberry_yasuo_base_wind005_out_back02.strawberryrebuild.scb",
            "size": 9960,
            "hash": "3e718883a590e00c",
            "champion": "yasuo",
            "skin": "base",
            "champion_skin": "yasuo_base"
          },
          {
            "filename": "strawberry_yasuo_base_wind005_out_front02.strawberryrebuild.scb",
            "type": "scb",
            "path": "SCB/strawberry_yasuo_base_wind005_out_front02.strawberryrebuild.scb",
            "size": 9960,
            "hash": "e6b101fdd2b1f65a",
            "champion": "yasuo",
            "skin": "base",
            "champion_skin": "yasuo_base"
          },
          {
            "filename": "strawberry_yasuo_base_wind006.strawberryrebuild.scb",
            "type": "scb",
            "path": "SCB/strawberry_yasuo_base_wind006.strawberryrebuild.scb",
            "size": 54912,
            "hash": "153b5108b7789ce2",
            "champion": "yasuo",
            "skin": "base",
            "champion_skin": "yasuo_base"
          },
          {
            "filename": "strawberry_yasuo_base_w_01.strawberryrebuild.scb",
            "type": "scb",
            "path": "SCB/strawberry_yasuo_base_w_01.strawberryrebuild.scb",
            "size": 13964,
            "hash": "aa974b5ddb73d60d",
            "champion": "yasuo",
            "skin": "base",
            "champion_skin": "yasuo_base"
          },
          {
            "filename": "strawberry_yasuo_base_w_02.strawberryrebuild.scb",
            "type": "scb",
            "path": "SCB/strawberry_yasuo_base_w_02.strawberryrebuild.scb",
            "size": 178216,
            "hash": "471dd1be89ddc0c9",
            "champion": "yasuo",
            "skin": "base",
            "champion_skin": "yasuo_base"
          },
          {
            "filename": "tft6_booms_yasuo_line02.mel.scb",
            "type": "scb",
            "path": "SCB/tft6_booms_yasuo_line02.mel.scb",
            "size": 11592,
            "hash": "3ebf91a51163574e",
            "champion": "yasuo",
            "skin": "base",
            "champion_skin": "yasuo_base"
          },
          {
            "filename": "tft6_booms_yasuo_line_weapon.tft_booms_briar_base.scb",
            "type": "scb",
            "path": "SCB/tft6_booms_yasuo_line_weapon.tft_booms_briar_base.scb",
            "size": 6712,
            "hash": "3095b5c039ea1181",
            "champion": "yasuo",
            "skin": "base",
            "champion_skin": "yasuo_base"
          },
          {
            "filename": "tft6_booms_yasuo_sphere01.scb",
            "type": "scb",
            "path": "SCB/tft6_booms_yasuo_sphere01.scb",
            "size": 54848,
            "hash": "826e63c492f1ec76",
            "champion": "yasuo",
            "skin": "base",
            "champion_skin": "yasuo_base"
          },
          {
            "filename": "tft6_booms_yasuo_tornado.scb",
            "type": "scb",
            "path": "SCB/tft6_booms_yasuo_tornado.scb",
            "size": 50016,
            "hash": "ab11e4077ce78170",
            "champion": "yasuo",
            "skin": "base",
            "champion_skin": "yasuo_base"
          },
          {
            "filename": "tft6_booms_yasuo_tornado03.scb",
            "type": "scb",
            "path": "SCB/tft6_booms_yasuo_tornado03.scb",
            "size": 39540,
            "hash": "b111862e427f7c76",
            "champion": "yasuo",
            "skin": "base",
            "champion_skin": "yasuo_base"
          },
          {
            "filename": "yasuo_base_e_big_tonado.scb",
            "type": "scb",
            "path": "SCB/yasuo_base_e_big_tonado.scb",
            "size": 46560,
            "hash": "97a169774f8c1bb6",
            "champion": "yasuo",
            "skin": "base",
            "champion_skin": "yasuo_base"
          },
          {
            "filename": "yasuo_base_e_dash_afterimage.scb",
            "type": "scb",
            "path": "SCB/yasuo_base_e_dash_afterimage.scb",
            "size": 334084,
            "hash": "3108ea53c081e75b",
            "champion": "yasuo",
            "skin": "base",
            "champion_skin": "yasuo_base"
          },
          {
            "filename": "yasuo_base_e_dash_timer.scb",
            "type": "scb",
            "path": "SCB/yasuo_base_e_dash_timer.scb",
            "size": 184920,
            "hash": "cdf4726fb953dcfd",
            "champion": "yasuo",
            "skin": "base",
            "champion_skin": "yasuo_base"
          },
          {
            "filename": "yasuo_base_passive_hit.scb",
            "type": "scb",
            "path": "SCB/yasuo_base_passive_hit.scb",
            "size": 83228,
            "hash": "f7553a6d0d517602",
            "champion": "yasuo",
            "skin": "base",
            "champion_skin": "yasuo_base"
          },
          {
            "filename": "yasuo_base_q_ground_rock.scb",
            "type": "scb",
            "path": "SCB/yasuo_base_q_ground_rock.scb",
            "size": 5732,
            "hash": "f1099f33d7cfbbce",
            "champion": "yasuo",
            "skin": "base",
            "champion_skin": "yasuo_base"
          },
          {
            "filename": "yasuo_base_q_second_swirl.scb",
            "type": "scb",
            "path": "SCB/yasuo_base_q_second_swirl.scb",
            "size": 37336,
            "hash": "17fc7527c2bea4d5",
            "champion": "yasuo",
            "skin": "base",
            "champion_skin": "yasuo_base"
          },
          {
            "filename": "yasuo_base_q_tornado_blade_cas.scb",
            "type": "scb",
            "path": "SCB/yasuo_base_q_tornado_blade_cas.scb",
            "size": 14276,
            "hash": "e6358827a75c5201",
            "champion": "yasuo",
            "skin": "base",
            "champion_skin": "yasuo_base"
          },
          {
            "filename": "yasuo_base_recall_wind.scb",
            "type": "scb",
            "path": "SCB/yasuo_base_recall_wind.scb",
            "size": 29928,
            "hash": "3ae68f6b3445b763",
            "champion": "yasuo",
            "skin": "base",
            "champion_skin": "yasuo_base"
          },
          {
            "filename": "yasuo_base_r_ground_blast.scb",
            "type": "scb",
            "path": "SCB/yasuo_base_r_ground_blast.scb",
            "size": 18828,
            "hash": "f93922b3f32e4946",
            "champion": "yasuo",
            "skin": "base",
            "champion_skin": "yasuo_base"
          },
          {
            "filename": "yasuo_skin01_r_wind_blast.scb",
            "type": "scb",
            "path": "SCB/yasuo_skin01_r_wind_blast.scb",
            "size": 74028,
            "hash": "e3c9c9dd3c61ec7c",
            "champion": "yasuo",
            "skin": "skin_01",
            "champion_skin": "yasuo_skin_01"
          },
          {
            "filename": "yasuo_skin02_dance_ring_01.scb",
            "type": "scb",
            "path": "SCB/yasuo_skin02_dance_ring_01.scb",
            "size": 8912,
            "hash": "30dffa0203d36745",
            "champion": "yasuo",
            "skin": "skin_02",
            "champion_skin": "yasuo_skin_02"
          },
          {
            "filename": "yasuo_skin02_eq_cube_01.scb",
            "type": "scb",
            "path": "SCB/yasuo_skin02_eq_cube_01.scb",
            "size": 1488,
            "hash": "7f64593432690b6a",
            "champion": "yasuo",
            "skin": "skin_02",
            "champion_skin": "yasuo_skin_02"
          },
          {
            "filename": "yasuo_skin02_eq_ring_01.scb",
            "type": "scb",
            "path": "SCB/yasuo_skin02_eq_ring_01.scb",
            "size": 7360,
            "hash": "e4016b24d73071c4",
            "champion": "yasuo",
            "skin": "skin_02",
            "champion_skin": "yasuo_skin_02"
          },
          {
            "filename": "yasuo_skin02_w_wall_01.scb",
            "type": "scb",
            "path": "SCB/yasuo_skin02_w_wall_01.scb",
            "size": 21644,
            "hash": "3ff8c4a8225ec34f",
            "champion": "yasuo",
            "skin": "skin_02",
            "champion_skin": "yasuo_skin_02"
          },
          {
            "filename": "yasuo_skin02_z_cube.scb",
            "type": "scb",
            "path": "SCB/yasuo_skin02_z_cube.scb",
            "size": 1596,
            "hash": "0624c5775d2f1342",
            "champion": "yasuo",
            "skin": "skin_02",
            "champion_skin": "yasuo_skin_02"
          },
          {
            "filename": "yasuo_skin02_z_ringflared_01.scb",
            "type": "scb",
            "path": "SCB/yasuo_skin02_z_ringflared_01.scb",
            "size": 69824,
            "hash": "ba65bc95cc2b6c65",
            "champion": "yasuo",
            "skin": "skin_02",
            "champion_skin": "yasuo_skin_02"
          },
          {
            "filename": "yasuo_skin02_z_ringflared_02.scb",
            "type": "scb",
            "path": "SCB/yasuo_skin02_z_ringflared_02.scb",
            "size": 97472,
            "hash": "3f686c7e4c09439c",
            "champion": "yasuo",
            "skin": "skin_02",
            "champion_skin": "yasuo_skin_02"
          },
          {
            "filename": "yasuo_skin02_z_ringflared_03.scb",
            "type": "scb",
            "path": "SCB/yasuo_skin02_z_ringflared_03.scb",
            "size": 97472,
            "hash": "09818491729f626e",
            "champion": "yasuo",
            "skin": "skin_02",
            "champion_skin": "yasuo_skin_02"
          },
          {
            "filename": "yasuo_skin03_e_big_tonado.scb",
            "type": "scb",
            "path": "SCB/yasuo_skin03_e_big_tonado.scb",
            "size": 46560,
            "hash": "3764590a54eb97f1",
            "champion": "yasuo",
            "skin": "skin_03",
            "champion_skin": "yasuo_skin_03"
          },
          {
            "filename": "yasuo_skin03_e_big_tonado_shape.scb",
            "type": "scb",
            "path": "SCB/yasuo_skin03_e_big_tonado_shape.scb",
            "size": 46560,
            "hash": "e668de72259e5471",
            "champion": "yasuo",
            "skin": "skin_03",
            "champion_skin": "yasuo_skin_03"
          },
          {
            "filename": "yasuo_skin03_e_dash_afterimage.scb",
            "type": "scb",
            "path": "SCB/yasuo_skin03_e_dash_afterimage.scb",
            "size": 334084,
            "hash": "afb26b0823cd3e38",
            "champion": "yasuo",
            "skin": "skin_03",
            "champion_skin": "yasuo_skin_03"
          },
          {
            "filename": "yasuo_skin03_e_dash_timer.scb",
            "type": "scb",
            "path": "SCB/yasuo_skin03_e_dash_timer.scb",
            "size": 184920,
            "hash": "6887264c54c2eee9",
            "champion": "yasuo",
            "skin": "skin_03",
            "champion_skin": "yasuo_skin_03"
          },
          {
            "filename": "yasuo_skin03_e_q_blade_trail.scb",
            "type": "scb",
            "path": "SCB/yasuo_skin03_e_q_blade_trail.scb",
            "size": 129576,
            "hash": "ee9b387ba1c1a127",
            "champion": "yasuo",
            "skin": "skin_03",
            "champion_skin": "yasuo_skin_03"
          },
          {
            "filename": "yasuo_skin03_passive_hit.scb",
            "type": "scb",
            "path": "SCB/yasuo_skin03_passive_hit.scb",
            "size": 83228,
            "hash": "93b2743176893c84",
            "champion": "yasuo",
            "skin": "skin_03",
            "champion_skin": "yasuo_skin_03"
          },
          {
            "filename": "yasuo_skin03_passive_wind.scb",
            "type": "scb",
            "path": "SCB/yasuo_skin03_passive_wind.scb",
            "size": 184920,
            "hash": "3164c653151e9afc",
            "champion": "yasuo",
            "skin": "skin_03",
            "champion_skin": "yasuo_skin_03"
          },
          {
            "filename": "yasuo_skin03_q_ground_rock.scb",
            "type": "scb",
            "path": "SCB/yasuo_skin03_q_ground_rock.scb",
            "size": 5732,
            "hash": "59c00a26d17f6c8a",
            "champion": "yasuo",
            "skin": "skin_03",
            "champion_skin": "yasuo_skin_03"
          },
          {
            "filename": "yasuo_skin03_q_knock_up_tar.scb",
            "type": "scb",
            "path": "SCB/yasuo_skin03_q_knock_up_tar.scb",
            "size": 9628,
            "hash": "64c29d2c8dfd1c7c",
            "champion": "yasuo",
            "skin": "skin_03",
            "champion_skin": "yasuo_skin_03"
          },
          {
            "filename": "yasuo_skin03_recall_center_bloodmoon.scb",
            "type": "scb",
            "path": "SCB/yasuo_skin03_recall_center_bloodmoon.scb",
            "size": 6936,
            "hash": "28166e911b37b754",
            "champion": "yasuo",
            "skin": "skin_03",
            "champion_skin": "yasuo_skin_03"
          },
          {
            "filename": "yasuo_skin03_r_ground_blast.scb",
            "type": "scb",
            "path": "SCB/yasuo_skin03_r_ground_blast.scb",
            "size": 18828,
            "hash": "dd529f1194d028f4",
            "champion": "yasuo",
            "skin": "skin_03",
            "champion_skin": "yasuo_skin_03"
          },
          {
            "filename": "yasuo_skin03_w_windwall_mesh.scb",
            "type": "scb",
            "path": "SCB/yasuo_skin03_w_windwall_mesh.scb",
            "size": 17776,
            "hash": "3619e808f68b6220",
            "champion": "yasuo",
            "skin": "skin_03",
            "champion_skin": "yasuo_skin_03"
          },
          {
            "filename": "yasuo_skin09_ba_swipe_01.scb",
            "type": "scb",
            "path": "SCB/yasuo_skin09_ba_swipe_01.scb",
            "size": 10096,
            "hash": "617e68c95adb35db",
            "champion": "yasuo",
            "skin": "skin_09",
            "champion_skin": "yasuo_skin_09"
          },
          {
            "filename": "yasuo_skin09_ba_swipe_02.scb",
            "type": "scb",
            "path": "SCB/yasuo_skin09_ba_swipe_02.scb",
            "size": 10992,
            "hash": "86ec3745676799da",
            "champion": "yasuo",
            "skin": "skin_09",
            "champion_skin": "yasuo_skin_09"
          },
          {
            "filename": "yasuo_skin09_ba_swipe_03.scb",
            "type": "scb",
            "path": "SCB/yasuo_skin09_ba_swipe_03.scb",
            "size": 10992,
            "hash": "6d127419fe2fda4c",
            "champion": "yasuo",
            "skin": "skin_09",
            "champion_skin": "yasuo_skin_09"
          },
          {
            "filename": "yasuo_skin09_ba_swipe_04.scb",
            "type": "scb",
            "path": "SCB/yasuo_skin09_ba_swipe_04.scb",
            "size": 8304,
            "hash": "fedf8bae128896e2",
            "champion": "yasuo",
            "skin": "skin_09",
            "champion_skin": "yasuo_skin_09"
          },
          {
            "filename": "yasuo_skin09_eq_swipe_01.scb",
            "type": "scb",
            "path": "SCB/yasuo_skin09_eq_swipe_01.scb",
            "size": 26112,
            "hash": "67395dd37a2758c5",
            "champion": "yasuo",
            "skin": "skin_09",
            "champion_skin": "yasuo_skin_09"
          },
          {
            "filename": "yasuo_skin09_q_geo_02.scb",
            "type": "scb",
            "path": "SCB/yasuo_skin09_q_geo_02.scb",
            "size": 105016,
            "hash": "1b36ce933f7754fb",
            "champion": "yasuo",
            "skin": "skin_09",
            "champion_skin": "yasuo_skin_09"
          },
          {
            "filename": "yasuo_skin09_q_ringsmoke_01.scb",
            "type": "scb",
            "path": "SCB/yasuo_skin09_q_ringsmoke_01.scb",
            "size": 34592,
            "hash": "4e2f276810b48fa9",
            "champion": "yasuo",
            "skin": "skin_09",
            "champion_skin": "yasuo_skin_09"
          },
          {
            "filename": "yasuo_skin09_q_swirl_01.scb",
            "type": "scb",
            "path": "SCB/yasuo_skin09_q_swirl_01.scb",
            "size": 53008,
            "hash": "37c5f56fef8afc6a",
            "champion": "yasuo",
            "skin": "skin_09",
            "champion_skin": "yasuo_skin_09"
          },
          {
            "filename": "yasuo_skin09_q_tornado2.scb",
            "type": "scb",
            "path": "SCB/yasuo_skin09_q_tornado2.scb",
            "size": 23408,
            "hash": "d3c113cb09637782",
            "champion": "yasuo",
            "skin": "skin_09",
            "champion_skin": "yasuo_skin_09"
          },
          {
            "filename": "yasuo_skin09_r_bigring_01.scb",
            "type": "scb",
            "path": "SCB/yasuo_skin09_r_bigring_01.scb",
            "size": 78912,
            "hash": "729187ea2de7c3e5",
            "champion": "yasuo",
            "skin": "skin_09",
            "champion_skin": "yasuo_skin_09"
          },
          {
            "filename": "yasuo_skin09_r_shadowpose_01.scb",
            "type": "scb",
            "path": "SCB/yasuo_skin09_r_shadowpose_01.scb",
            "size": 879948,
            "hash": "d1c9429b7e6b5283",
            "champion": "yasuo",
            "skin": "skin_09",
            "champion_skin": "yasuo_skin_09"
          },
          {
            "filename": "yasuo_skin09_r_swipe_01.scb",
            "type": "scb",
            "path": "SCB/yasuo_skin09_r_swipe_01.scb",
            "size": 9200,
            "hash": "ecb5d9ed890dd024",
            "champion": "yasuo",
            "skin": "skin_09",
            "champion_skin": "yasuo_skin_09"
          },
          {
            "filename": "yasuo_skin09_w_crackemitter_01.scb",
            "type": "scb",
            "path": "SCB/yasuo_skin09_w_crackemitter_01.scb",
            "size": 3352,
            "hash": "ccfd731dced07dde",
            "champion": "yasuo",
            "skin": "skin_09",
            "champion_skin": "yasuo_skin_09"
          },
          {
            "filename": "yasuo_skin09_w_wallbase_01.scb",
            "type": "scb",
            "path": "SCB/yasuo_skin09_w_wallbase_01.scb",
            "size": 17544,
            "hash": "e38c91799203b2cf",
            "champion": "yasuo",
            "skin": "skin_09",
            "champion_skin": "yasuo_skin_09"
          },
          {
            "filename": "yasuo_skin09_w_wallcap_01.scb",
            "type": "scb",
            "path": "SCB/yasuo_skin09_w_wallcap_01.scb",
            "size": 12592,
            "hash": "035d03cf4958bf6b",
            "champion": "yasuo",
            "skin": "skin_09",
            "champion_skin": "yasuo_skin_09"
          },
          {
            "filename": "yasuo_skin09_w_wallmid_02.scb",
            "type": "scb",
            "path": "SCB/yasuo_skin09_w_wallmid_02.scb",
            "size": 29704,
            "hash": "0fe0defaa3edf5ef",
            "champion": "yasuo",
            "skin": "skin_09",
            "champion_skin": "yasuo_skin_09"
          },
          {
            "filename": "yasuo_skin09_w_wallmid_03.scb",
            "type": "scb",
            "path": "SCB/yasuo_skin09_w_wallmid_03.scb",
            "size": 29704,
            "hash": "c6426e7f49e0bd26",
            "champion": "yasuo",
            "skin": "skin_09",
            "champion_skin": "yasuo_skin_09"
          },
          {
            "filename": "yasuo_skin09_w_wallsmoke_01.scb",
            "type": "scb",
            "path": "SCB/yasuo_skin09_w_wallsmoke_01.scb",
            "size": 29704,
            "hash": "d4ac88c6f63e292b",
            "champion": "yasuo",
            "skin": "skin_09",
            "champion_skin": "yasuo_skin_09"
          },
          {
            "filename": "yasuo_skin09_z_ring_01.scb",
            "type": "scb",
            "path": "SCB/yasuo_skin09_z_ring_01.scb",
            "size": 34592,
            "hash": "cc8d800988c774bd",
            "champion": "yasuo",
            "skin": "skin_09",
            "champion_skin": "yasuo_skin_09"
          },
          {
            "filename": "yasuo_skin10_attack-1_trail_00.scb",
            "type": "scb",
            "path": "SCB/yasuo_skin10_attack-1_trail_00.scb",
            "size": 15528,
            "hash": "2f1932f43117ef85",
            "champion": "yasuo",
            "skin": "skin_10",
            "champion_skin": "yasuo_skin_10"
          },
          {
            "filename": "yasuo_skin10_q_windmesh01.scb",
            "type": "scb",
            "path": "SCB/yasuo_skin10_q_windmesh01.scb",
            "size": 11824,
            "hash": "150f4eb977b27a0d",
            "champion": "yasuo",
            "skin": "skin_10",
            "champion_skin": "yasuo_skin_10"
          },
          {
            "filename": "yasuo_skin10_q_windmesh02.scb",
            "type": "scb",
            "path": "SCB/yasuo_skin10_q_windmesh02.scb",
            "size": 41408,
            "hash": "c2dcf0aeefb46b65",
            "champion": "yasuo",
            "skin": "skin_10",
            "champion_skin": "yasuo_skin_10"
          },
          {
            "filename": "yasuo_skin10_r_swipe01.scb",
            "type": "scb",
            "path": "SCB/yasuo_skin10_r_swipe01.scb",
            "size": 5792,
            "hash": "123f40e1bf8392e4",
            "champion": "yasuo",
            "skin": "skin_10",
            "champion_skin": "yasuo_skin_10"
          },
          {
            "filename": "yasuo_skin10_r_swipe02.scb",
            "type": "scb",
            "path": "SCB/yasuo_skin10_r_swipe02.scb",
            "size": 5792,
            "hash": "4f147e3eee0402e4",
            "champion": "yasuo",
            "skin": "skin_10",
            "champion_skin": "yasuo_skin_10"
          },
          {
            "filename": "yasuo_skin10_r_swipe03.scb",
            "type": "scb",
            "path": "SCB/yasuo_skin10_r_swipe03.scb",
            "size": 5792,
            "hash": "29a79d5441dd2816",
            "champion": "yasuo",
            "skin": "skin_10",
            "champion_skin": "yasuo_skin_10"
          },
          {
            "filename": "yasuo_skin10_w_ring_geo.scb",
            "type": "scb",
            "path": "SCB/yasuo_skin10_w_ring_geo.scb",
            "size": 26672,
            "hash": "9591fc91a27f5d3e",
            "champion": "yasuo",
            "skin": "skin_10",
            "champion_skin": "yasuo_skin_10"
          },
          {
            "filename": "yasuo_skin10_w_wall_01a.scb",
            "type": "scb",
            "path": "SCB/yasuo_skin10_w_wall_01a.scb",
            "size": 14072,
            "hash": "6934cc8204f949bf",
            "champion": "yasuo",
            "skin": "skin_10",
            "champion_skin": "yasuo_skin_10"
          },
          {
            "filename": "yasuo_skin10_w_wall_02_lower.scb",
            "type": "scb",
            "path": "SCB/yasuo_skin10_w_wall_02_lower.scb",
            "size": 16032,
            "hash": "1037209b02c7da28",
            "champion": "yasuo",
            "skin": "skin_10",
            "champion_skin": "yasuo_skin_10"
          },
          {
            "filename": "yasuo_skin10_w_wall_side_1.scb",
            "type": "scb",
            "path": "SCB/yasuo_skin10_w_wall_side_1.scb",
            "size": 7960,
            "hash": "bd70aaab6e404351",
            "champion": "yasuo",
            "skin": "skin_10",
            "champion_skin": "yasuo_skin_10"
          },
          {
            "filename": "yasuo_skin18_q_tornadomesh02.scb",
            "type": "scb",
            "path": "SCB/yasuo_skin18_q_tornadomesh02.scb",
            "size": 32292,
            "hash": "53b0bd3638e502fd",
            "champion": "yasuo",
            "skin": "skin_18",
            "champion_skin": "yasuo_skin_18"
          },
          {
            "filename": "yasuo_skin18_w_wallmesh02.scb",
            "type": "scb",
            "path": "SCB/yasuo_skin18_w_wallmesh02.scb",
            "size": 12112,
            "hash": "2b7ab5fcd10bee75",
            "champion": "yasuo",
            "skin": "skin_18",
            "champion_skin": "yasuo_skin_18"
          },
          {
            "filename": "yasuo_skin45_recall_anim_swipe01.scb",
            "type": "scb",
            "path": "SCB/yasuo_skin45_recall_anim_swipe01.scb",
            "size": 7408,
            "hash": "f12affdae7460c63",
            "champion": "yasuo",
            "skin": "skin_45",
            "champion_skin": "yasuo_skin_45"
          },
          {
            "filename": "yasuo_skin45_recall_anim_swipe02.scb",
            "type": "scb",
            "path": "SCB/yasuo_skin45_recall_anim_swipe02.scb",
            "size": 7856,
            "hash": "edcacf503e882924",
            "champion": "yasuo",
            "skin": "skin_45",
            "champion_skin": "yasuo_skin_45"
          },
          {
            "filename": "yasuo_skin54_eq_swipe.scb",
            "type": "scb",
            "path": "SCB/yasuo_skin54_eq_swipe.scb",
            "size": 4248,
            "hash": "b392ef6c50b02537",
            "champion": "yasuo",
            "skin": "skin_54",
            "champion_skin": "yasuo_skin_54"
          },
          {
            "filename": "yasuo_skin54_w_windwall_01.scb",
            "type": "scb",
            "path": "SCB/yasuo_skin54_w_windwall_01.scb",
            "size": 8176,
            "hash": "e3cb7d7691b92a1b",
            "champion": "yasuo",
            "skin": "skin_54",
            "champion_skin": "yasuo_skin_54"
          },
          {
            "filename": "yasuo_skin54_w_windwall_dragon03.scb",
            "type": "scb",
            "path": "SCB/yasuo_skin54_w_windwall_dragon03.scb",
            "size": 8176,
            "hash": "d44c9b328f076e48",
            "champion": "yasuo",
            "skin": "skin_54",
            "champion_skin": "yasuo_skin_54"
          },
          {
            "filename": "yasuo_skin55_shoulder_gradient02.scb",
            "type": "scb",
            "path": "SCB/yasuo_skin55_shoulder_gradient02.scb",
            "size": 13488,
            "hash": "3a35d76337c20b73",
            "champion": "yasuo",
            "skin": "skin_55",
            "champion_skin": "yasuo_skin_55"
          },
          {
            "filename": "yasuo_skin56_e_yasuomesh_01.scb",
            "type": "scb",
            "path": "SCB/yasuo_skin56_e_yasuomesh_01.scb",
            "size": 1739052,
            "hash": "74c0003f6c001284",
            "champion": "yasuo",
            "skin": "skin_56",
            "champion_skin": "yasuo_skin_56"
          },
          {
            "filename": "yasuo_skin56_q_seal_01.scb",
            "type": "scb",
            "path": "SCB/yasuo_skin56_q_seal_01.scb",
            "size": 19272,
            "hash": "f9b8393ed2bf21af",
            "champion": "yasuo",
            "skin": "skin_56",
            "champion_skin": "yasuo_skin_56"
          },
          {
            "filename": "yasuo_skin56_q_tornado_blade_cas.scb",
            "type": "scb",
            "path": "SCB/yasuo_skin56_q_tornado_blade_cas.scb",
            "size": 13536,
            "hash": "2653ee4f25e73e33",
            "champion": "yasuo",
            "skin": "skin_56",
            "champion_skin": "yasuo_skin_56"
          },
          {
            "filename": "yasuo_skin56_r_sword_wind2.scb",
            "type": "scb",
            "path": "SCB/yasuo_skin56_r_sword_wind2.scb",
            "size": 35216,
            "hash": "18ee7375aeef63bb",
            "champion": "yasuo",
            "skin": "skin_56",
            "champion_skin": "yasuo_skin_56"
          },
          {
            "filename": "yasuo_skin56_w_wallmesh_01.scb",
            "type": "scb",
            "path": "SCB/yasuo_skin56_w_wallmesh_01.scb",
            "size": 33008,
            "hash": "2c05d7cd72ad0417",
            "champion": "yasuo",
            "skin": "skin_56",
            "champion_skin": "yasuo_skin_56"
          },
          {
            "filename": "yasuo_skin56_z_cas_hitground_01.scb",
            "type": "scb",
            "path": "SCB/yasuo_skin56_z_cas_hitground_01.scb",
            "size": 71072,
            "hash": "95d44ae40c7c0f5d",
            "champion": "yasuo",
            "skin": "skin_56",
            "champion_skin": "yasuo_skin_56"
          },
          {
            "filename": "yasuo_skin56_z_swipemesh_01.scb",
            "type": "scb",
            "path": "SCB/yasuo_skin56_z_swipemesh_01.scb",
            "size": 30192,
            "hash": "e4844d1f98284e6b",
            "champion": "yasuo",
            "skin": "skin_56",
            "champion_skin": "yasuo_skin_56"
          },
          {
            "filename": "yasuo_skin56_z_swipemesh_02.scb",
            "type": "scb",
            "path": "SCB/yasuo_skin56_z_swipemesh_02.scb",
            "size": 30192,
            "hash": "6703ce8e6291e336",
            "champion": "yasuo",
            "skin": "skin_56",
            "champion_skin": "yasuo_skin_56"
          },
          {
            "filename": "yasuo_skin57_flameburst.domina.scb",
            "type": "scb",
            "path": "SCB/yasuo_skin57_flameburst.domina.scb",
            "size": 23408,
            "hash": "fff777e7c3129c8a",
            "champion": "yasuo",
            "skin": "skin_57",
            "champion_skin": "yasuo_skin_57"
          },
          {
            "filename": "yasuo_skin57_q_buf_logo_01.scb",
            "type": "scb",
            "path": "SCB/yasuo_skin57_q_buf_logo_01.scb",
            "size": 10984,
            "hash": "4f819bbe2ff6e0d1",
            "champion": "yasuo",
            "skin": "skin_57",
            "champion_skin": "yasuo_skin_57"
          },
          {
            "filename": "yasuo_skin57_q_buf_logo_crystal_01.scb",
            "type": "scb",
            "path": "SCB/yasuo_skin57_q_buf_logo_crystal_01.scb",
            "size": 2296,
            "hash": "d04d9f1009e5174e",
            "champion": "yasuo",
            "skin": "skin_57",
            "champion_skin": "yasuo_skin_57"
          },
          {
            "filename": "yasuo_skin57_q_crystal_01.scb",
            "type": "scb",
            "path": "SCB/yasuo_skin57_q_crystal_01.scb",
            "size": 2496,
            "hash": "8e26a4504366d970",
            "champion": "yasuo",
            "skin": "skin_57",
            "champion_skin": "yasuo_skin_57"
          },
          {
            "filename": "yasuo_skin57_q_crystal_gouyu_01.scb",
            "type": "scb",
            "path": "SCB/yasuo_skin57_q_crystal_gouyu_01.scb",
            "size": 73120,
            "hash": "1990e4963c3cd266",
            "champion": "yasuo",
            "skin": "skin_57",
            "champion_skin": "yasuo_skin_57"
          },
          {
            "filename": "yasuo_skin57_r_canying_01.scb",
            "type": "scb",
            "path": "SCB/yasuo_skin57_r_canying_01.scb",
            "size": 250920,
            "hash": "f6ca652ae0e7cf15",
            "champion": "yasuo",
            "skin": "skin_57",
            "champion_skin": "yasuo_skin_57"
          },
          {
            "filename": "yasuo_skin57_r_crystal_ground_01.scb",
            "type": "scb",
            "path": "SCB/yasuo_skin57_r_crystal_ground_01.scb",
            "size": 17168,
            "hash": "c272874f2c673e36",
            "champion": "yasuo",
            "skin": "skin_57",
            "champion_skin": "yasuo_skin_57"
          },
          {
            "filename": "yasuo_skin57_w_crystal_ground_01.scb",
            "type": "scb",
            "path": "SCB/yasuo_skin57_w_crystal_ground_01.scb",
            "size": 5632,
            "hash": "5493fc4ebd5d6b27",
            "champion": "yasuo",
            "skin": "skin_57",
            "champion_skin": "yasuo_skin_57"
          },
          {
            "filename": "yasuo_skin68_basic_attack_3.scb",
            "type": "scb",
            "path": "SCB/yasuo_skin68_basic_attack_3.scb",
            "size": 38796,
            "hash": "75c42fc634f56705",
            "champion": "yasuo",
            "skin": "skin_68",
            "champion_skin": "yasuo_skin_68"
          },
          {
            "filename": "yasuo_skin68_basic_attack_6.scb",
            "type": "scb",
            "path": "SCB/yasuo_skin68_basic_attack_6.scb",
            "size": 38796,
            "hash": "9c77ecebc38282bd",
            "champion": "yasuo",
            "skin": "skin_68",
            "champion_skin": "yasuo_skin_68"
          },
          {
            "filename": "yasuo_skin68_basic_attack_7.scb",
            "type": "scb",
            "path": "SCB/yasuo_skin68_basic_attack_7.scb",
            "size": 38796,
            "hash": "c369eb7b6837f423",
            "champion": "yasuo",
            "skin": "skin_68",
            "champion_skin": "yasuo_skin_68"
          },
          {
            "filename": "yasuo_skin68_lightning_swipe_01.scb",
            "type": "scb",
            "path": "SCB/yasuo_skin68_lightning_swipe_01.scb",
            "size": 38796,
            "hash": "87020c53ebe8b1e0",
            "champion": "yasuo",
            "skin": "skin_68",
            "champion_skin": "yasuo_skin_68"
          },
          {
            "filename": "yasuo_skin68_q_fire.scb",
            "type": "scb",
            "path": "SCB/yasuo_skin68_q_fire.scb",
            "size": 30304,
            "hash": "972255695b5c2725",
            "champion": "yasuo",
            "skin": "skin_68",
            "champion_skin": "yasuo_skin_68"
          },
          {
            "filename": "yasuo_skin68_r_swipe_01.scb",
            "type": "scb",
            "path": "SCB/yasuo_skin68_r_swipe_01.scb",
            "size": 38796,
            "hash": "2b6db13502f313f3",
            "champion": "yasuo",
            "skin": "skin_68",
            "champion_skin": "yasuo_skin_68"
          },
          {
            "filename": "yasuo_skin68_r_swipe_02.scb",
            "type": "scb",
            "path": "SCB/yasuo_skin68_r_swipe_02.scb",
            "size": 38796,
            "hash": "5b4ce4554ae6c0f7",
            "champion": "yasuo",
            "skin": "skin_68",
            "champion_skin": "yasuo_skin_68"
          },
          {
            "filename": "yasuo_skin68_r_swipe_03.scb",
            "type": "scb",
            "path": "SCB/yasuo_skin68_r_swipe_03.scb",
            "size": 38796,
            "hash": "2d3d140ced26290d",
            "champion": "yasuo",
            "skin": "skin_68",
            "champion_skin": "yasuo_skin_68"
          },
          {
            "filename": "yasuo_skin68_w_side_wind_wall_03.scb",
            "type": "scb",
            "path": "SCB/yasuo_skin68_w_side_wind_wall_03.scb",
            "size": 8852,
            "hash": "96cfb2e1a39dd78f",
            "champion": "yasuo",
            "skin": "skin_68",
            "champion_skin": "yasuo_skin_68"
          },
          {
            "filename": "yasuo_skin68_w_wind_wall_06.scb",
            "type": "scb",
            "path": "SCB/yasuo_skin68_w_wind_wall_06.scb",
            "size": 23552,
            "hash": "57e838f576e012c5",
            "champion": "yasuo",
            "skin": "skin_68",
            "champion_skin": "yasuo_skin_68"
          },
          {
            "filename": "yasuo_skin77_q3_wind_ready_ground02_1.skins_yasuo_skin77.scb",
            "type": "scb",
            "path": "SCB/yasuo_skin77_q3_wind_ready_ground02_1.skins_yasuo_skin77.scb",
            "size": 56768,
            "hash": "739106bf91ae40b3",
            "champion": "yasuo",
            "skin": "skin_77",
            "champion_skin": "yasuo_skin_77"
          },
          {
            "filename": "yasuo_skin77_q_windstrike_shape001.skins_yasuo_skin77.scb",
            "type": "scb",
            "path": "SCB/yasuo_skin77_q_windstrike_shape001.skins_yasuo_skin77.scb",
            "size": 32352,
            "hash": "ece6a8a6aa3ead85",
            "champion": "yasuo",
            "skin": "skin_77",
            "champion_skin": "yasuo_skin_77"
          },
          {
            "filename": "yasuo_skin77_r_land_tar_crack001.skins_yasuo_skin77.scb",
            "type": "scb",
            "path": "SCB/yasuo_skin77_r_land_tar_crack001.skins_yasuo_skin77.scb",
            "size": 19488,
            "hash": "b7c15086a89e2d9a",
            "champion": "yasuo",
            "skin": "skin_77",
            "champion_skin": "yasuo_skin_77"
          },
          {
            "filename": "yasuo_skin77_r_land_tar_crack002.skins_yasuo_skin77.scb",
            "type": "scb",
            "path": "SCB/yasuo_skin77_r_land_tar_crack002.skins_yasuo_skin77.scb",
            "size": 32352,
            "hash": "53e9a5c1353713f6",
            "champion": "yasuo",
            "skin": "skin_77",
            "champion_skin": "yasuo_skin_77"
          },
          {
            "filename": "yasuo_skin77_r_land_tar_cylinder01.skins_yasuo_skin77.scb",
            "type": "scb",
            "path": "SCB/yasuo_skin77_r_land_tar_cylinder01.skins_yasuo_skin77.scb",
            "size": 23072,
            "hash": "d3a1c7aa82f2e09d",
            "champion": "yasuo",
            "skin": "skin_77",
            "champion_skin": "yasuo_skin_77"
          },
          {
            "filename": "yasuo_skin77_r_land_tar_halfsphere03.skins_yasuo_skin77.scb",
            "type": "scb",
            "path": "SCB/yasuo_skin77_r_land_tar_halfsphere03.skins_yasuo_skin77.scb",
            "size": 16792,
            "hash": "512a18d5e970999a",
            "champion": "yasuo",
            "skin": "skin_77",
            "champion_skin": "yasuo_skin_77"
          },
          {
            "filename": "yasuo_skin77_r_land_tar_ring02.skins_yasuo_skin77.scb",
            "type": "scb",
            "path": "SCB/yasuo_skin77_r_land_tar_ring02.skins_yasuo_skin77.scb",
            "size": 38712,
            "hash": "92a53066003f3993",
            "champion": "yasuo",
            "skin": "skin_77",
            "champion_skin": "yasuo_skin_77"
          },
          {
            "filename": "yasuo_skin77_wind005_out_back.skins_yasuo_skin77.scb",
            "type": "scb",
            "path": "SCB/yasuo_skin77_wind005_out_back.skins_yasuo_skin77.scb",
            "size": 9960,
            "hash": "e20cd13fefb6eda8",
            "champion": "yasuo",
            "skin": "skin_77",
            "champion_skin": "yasuo_skin_77"
          },
          {
            "filename": "yasuo_skin77_wind005_out_back03.skins_yasuo_skin77.scb",
            "type": "scb",
            "path": "SCB/yasuo_skin77_wind005_out_back03.skins_yasuo_skin77.scb",
            "size": 17360,
            "hash": "14c66ade8c81836f",
            "champion": "yasuo",
            "skin": "skin_77",
            "champion_skin": "yasuo_skin_77"
          },
          {
            "filename": "yasuo_skin77_wind005_out_front.skins_yasuo_skin77.scb",
            "type": "scb",
            "path": "SCB/yasuo_skin77_wind005_out_front.skins_yasuo_skin77.scb",
            "size": 9960,
            "hash": "e391fc555465da22",
            "champion": "yasuo",
            "skin": "skin_77",
            "champion_skin": "yasuo_skin_77"
          },
          {
            "filename": "yasuo_skin77_wind005_out_front03.skins_yasuo_skin77.scb",
            "type": "scb",
            "path": "SCB/yasuo_skin77_wind005_out_front03.skins_yasuo_skin77.scb",
            "size": 17360,
            "hash": "6f7f46e83c484bac",
            "champion": "yasuo",
            "skin": "skin_77",
            "champion_skin": "yasuo_skin_77"
          },
          {
            "filename": "yasuo_skin87_r_shadowpose2.skins_yasuo_skin87.scb",
            "type": "scb",
            "path": "SCB/yasuo_skin87_r_shadowpose2.skins_yasuo_skin87.scb",
            "size": 1599488,
            "hash": "629c9f688c0e19f3",
            "champion": "yasuo",
            "skin": "skin_87",
            "champion_skin": "yasuo_skin_87"
          },
          {
            "filename": "yasuo_skin87_w_eye.skins_yasuo_skin87.scb",
            "type": "scb",
            "path": "SCB/yasuo_skin87_w_eye.skins_yasuo_skin87.scb",
            "size": 14288,
            "hash": "1532284f838ecb0e",
            "champion": "yasuo",
            "skin": "skin_87",
            "champion_skin": "yasuo_skin_87"
          },
          {
            "filename": "yasuo_w_windwall_behind_mesh.scb",
            "type": "scb",
            "path": "SCB/yasuo_w_windwall_behind_mesh.scb",
            "size": 23440,
            "hash": "d12c2ec1bc6d2cbc",
            "champion": "yasuo",
            "skin": "base",
            "champion_skin": "yasuo_base"
          },
          {
            "filename": "yasuo_w_windwall_mesh.scb",
            "type": "scb",
            "path": "SCB/yasuo_w_windwall_mesh.scb",
            "size": 23440,
            "hash": "f36f9198f973e76c",
            "champion": "yasuo",
            "skin": "base",
            "champion_skin": "yasuo_base"
          },
          {
            "filename": "yasuo_w_windwall_side_mesh.scb",
            "type": "scb",
            "path": "SCB/yasuo_w_windwall_side_mesh.scb",
            "size": 46428,
            "hash": "8cce7a2f7958ebfd",
            "champion": "yasuo",
            "skin": "base",
            "champion_skin": "yasuo_base"
          },
          {
            "filename": "yasuo_w_windwall_top_mesh.scb",
            "type": "scb",
            "path": "SCB/yasuo_w_windwall_top_mesh.scb",
            "size": 33608,
            "hash": "9049bbdbe013d09e",
            "champion": "yasuo",
            "skin": "base",
            "champion_skin": "yasuo_base"
          },
          {
            "filename": "yone_skin35_recall_yasuo_mesh.scb",
            "type": "scb",
            "path": "SCB/yone_skin35_recall_yasuo_mesh.scb",
            "size": 376044,
            "hash": "dc3e1c9e18fbd0ab",
            "champion": "yasuo",
            "skin": "skin_35",
            "champion_skin": "yasuo_skin_35"
          }
        ]
      }
    }
  },
  "usage_examples": {
    "quick_search": "Pour chercher un fichier: lookup[filename] = path",
    "github_download": "Pour tlcharger: github_base_url + download_map[filename]['path']"
  }
}